README
setup.py
bin/covergrabber
cover_grabber/__init__.py
cover_grabber.egg-info/PKG-INFO
cover_grabber.egg-info/SOURCES.txt
cover_grabber.egg-info/dependency_links.txt
cover_grabber.egg-info/requires.txt
cover_grabber.egg-info/top_level.txt
cover_grabber/downloader/__init__.py
cover_grabber/downloader/lastfm_downloader.py
cover_grabber/handler/__init__.py
cover_grabber/handler/flac_handler.py
cover_grabber/handler/handler.py
cover_grabber/handler/handler_factory.py
cover_grabber/handler/mp3_handler.py
cover_grabber/handler/ogg_handler.py
cover_grabber/logging/__init__.py
cover_grabber/logging/config.py
cover_grabber/os/__init__.py
cover_grabber/os/media_dir_walker.py