Metadata-Version: 1.0
Name: cover-grabber
Version: 1.2.0
Summary: Recursively traverse media directory and download album art
Home-page: https://sourceforge.net/projects/covergrabber/
Author: Jayson Vaughn
Author-email: vaughn.jayson@gmail.com
License: GNU GPL v3
Platform: UNKNOWN
